fontnome/__init__.py
fontnome/__main__.py
fontnome/_version.py
fontnome/core.py
fontnome/utils.py
fontnome-1.0.2.dist-info/METADATA
fontnome-1.0.2.dist-info/WHEEL
fontnome-1.0.2.dist-info/entry_points.txt
fontnome-1.0.2.dist-info/licenses/LICENSE
fontnome-1.0.2.dist-info/RECORD
