Metadata-Version: 2.4
Name: fontnome
Version: 1.0.2
Summary: CLI tool for modifying font family names in OpenType/TrueType fonts
Project-URL: Homepage, https://github.com/fontlaborg/fontnome
Project-URL: Repository, https://github.com/fontlaborg/fontnome
Project-URL: Issues, https://github.com/fontlaborg/fontnome/issues
Author: Fontlab Ltd.
License: Apache-2.0
License-File: LICENSE
Classifier: Development Status :: 3 - Alpha
Classifier: Intended Audience :: Developers
Classifier: License :: OSI Approved :: Apache Software License
Classifier: Programming Language :: Python :: 3
Classifier: Programming Language :: Python :: 3.12
Classifier: Topic :: Multimedia :: Graphics :: Graphics Conversion
Classifier: Topic :: Text Processing :: Fonts
Requires-Python: >=3.12
Requires-Dist: fire>=0.6.0
Requires-Dist: fonttools>=4.50.0
Requires-Dist: loguru>=0.7.0
Provides-Extra: dev
Requires-Dist: mypy>=1.8.0; extra == 'dev'
Requires-Dist: pytest-cov>=6.0.0; extra == 'dev'
Requires-Dist: pytest>=8.0.0; extra == 'dev'
